hashkit/__init__.py
hashkit/analyzer.py
hashkit/cli.py
hashkit/cracker.py
hashkit/exceptions.py
hashkit/identifier.py
hashkit/models.py
hashkit/utils.py
hashkit/wordlists.py
hashkit-1.0.0.dist-info/licenses/LICENSE
hashkit-1.0.0.dist-info/METADATA
hashkit-1.0.0.dist-info/WHEEL
hashkit-1.0.0.dist-info/entry_points.txt
hashkit-1.0.0.dist-info/top_level.txt
hashkit-1.0.0.dist-info/RECORD
